ligas/__init__.py
ligas/entity_config.py
ligas/exceptions.py
ligas/fbref.py
ligas/install_hook.py
ligas/logger.py
ligas/utils.py
ligas-1.0.7.dist-info/METADATA
ligas-1.0.7.dist-info/WHEEL
ligas-1.0.7.dist-info/top_level.txt
ligas-1.0.7.dist-info/RECORD
