Metadata-Version: 2.1
Name: ligas
Version: 1.0.7
Summary: fetch soccer data with different ip and web browser
Author: edjinedja
Author-email: automaticall06@gmail.com
Project-URL: Bug Tracker, https://github.com/edjinedja/ligas/issues
Keywords: python,soccer,data,ligues,api,football
Classifier: Development Status :: 1 - Planning
Classifier: Intended Audience :: Developers
Classifier: Programming Language :: Python :: 3
Classifier: Operating System :: OS Independent
Requires-Dist: requests
Requires-Dist: beautifulsoup4
Requires-Dist: lxml
Requires-Dist: pyYAML
Requires-Dist: python-box
Requires-Dist: tqdm
Requires-Dist: ensure
Requires-Dist: numpy
Requires-Dist: pandas
Requires-Dist: joblib
Requires-Dist: pyfiglet
